Metadata-Version: 2.4
Name: cargo2rpm
Version: 0.3.0
Summary: Translation layer between cargo and RPM
Author-email: Fedora Rust SIG <rust@lists.fedoraproject.org>
License: MIT
Project-URL: homepage, https://codeberg.org/rust2rpm/cargo2rpm
Keywords: rpm,cargo,rust
Classifier: Development Status :: 5 - Production/Stable
Classifier: Intended Audience :: Developers
Classifier: Operating System :: POSIX :: Linux
Classifier: Programming Language :: Python :: 3 :: Only
Classifier: Programming Language :: Python :: 3.10
Classifier: Programming Language :: Python :: 3.11
Classifier: Programming Language :: Python :: 3.12
Classifier: Programming Language :: Python :: 3.13
Classifier: Programming Language :: Python :: 3.14
Classifier: Topic :: Software Development :: Build Tools
Classifier: Topic :: System :: Software Distribution
Classifier: Topic :: Utilities
Requires-Python: >=3.10
License-File: LICENSE
Dynamic: license-file
